osmxtract/__init__.py
osmxtract/cli.py
osmxtract/errors.py
osmxtract/location.py
osmxtract/overpass.py
osmxtract/seas.py
osmxtract-0.0.1.dist-info/METADATA
osmxtract-0.0.1.dist-info/RECORD
osmxtract-0.0.1.dist-info/WHEEL
osmxtract-0.0.1.dist-info/entry_points.txt
osmxtract-0.0.1.dist-info/top_level.txt
