Metadata-Version: 2.1
Name: osmxtract
Version: 0.0.1
Summary: Extract vector and raster data from OSM.
Home-page: https://github.com/yannforget/osmxtract
Author: Yann Forget
Author-email: yannforget@mailbox.org
License: UNKNOWN
Keywords: earth observation,gis,openstreetmap
Platform: UNKNOWN
Classifier: Development Status :: 3 - Alpha
Classifier: Intended Audience :: Developers
Classifier: Intended Audience :: Science/Research
Classifier: Topic :: Scientific/Engineering :: GIS
Classifier: License :: OSI Approved :: MIT License
Classifier: Programming Language :: Python :: 3
Classifier: Programming Language :: Python :: 3.6
Requires-Dist: requests
Requires-Dist: click
Requires-Dist: pyproj
Requires-Dist: geojson
Requires-Dist: shapely
Requires-Dist: fiona
Requires-Dist: rasterio
Requires-Dist: geopy
Requires-Dist: tqdm
Requires-Dist: appdirs
